text_only_scanner/__init__.py
text_only_scanner/cli.py
text_only_scanner/detector.py
text_only_scanner-0.1.1.dist-info/licenses/LICENSE
text_only_scanner-0.1.1.dist-info/METADATA
text_only_scanner-0.1.1.dist-info/WHEEL
text_only_scanner-0.1.1.dist-info/entry_points.txt
text_only_scanner-0.1.1.dist-info/top_level.txt
text_only_scanner-0.1.1.dist-info/RECORD
