Metadata-Version: 2.4
Name: text_only_scanner
Version: 0.1.1
Summary: Ensure only human readable text files are in a directory.
Author: Moses Liao
License: MIT
Classifier: Programming Language :: Python :: 3
Classifier: License :: OSI Approved :: MIT License
Classifier: Operating System :: OS Independent
Requires-Python: >=3.8
License-File: LICENSE
Dynamic: license-file
